hejmdal/__init__.py
hejmdal/__main__.py
hejmdal/base.py
hejmdal/datacalls.py
hejmdal/formatting.py
hejmdal/forms.py
hejmdal/log.py
hejmdal/main.py
hejmdal/operations.py
hejmdal-0.1.7.dist-info/LICENSE
hejmdal-0.1.7.dist-info/LICENSE.txt
hejmdal-0.1.7.dist-info/METADATA
hejmdal-0.1.7.dist-info/WHEEL
hejmdal-0.1.7.dist-info/top_level.txt
hejmdal-0.1.7.dist-info/RECORD
