Metadata-Version: 2.1
Name: hejmdal
Version: 0.1.7
Summary: Hejmdal is used to bridge the gap between files, databases, servers and in memory content. It is mainly written for variometer data for geomagnetism.
Home-page: https://github.com/asknevegamby/Hejmdal
Author: Ask Neve Gamby
Author-email: aknvg@space.dtu.dk
Maintainer: Thom R. Edwards
Maintainer-email: hardsnow@space.dtu.dk
License: None
Download-URL: https://github.com/asknevegamby/Hejmdal/archive/0.1.6.tar.gz
Keywords: sql,download,file format,backend,magnetic field
Platform: UNKNOWN
Classifier: Development Status :: 2 - Pre-Alpha
Classifier: Intended Audience :: Science/Research
Classifier: Programming Language :: Python
Classifier: Programming Language :: Python :: 3
Classifier: Programming Language :: Python :: 3.4
Classifier: Programming Language :: Python :: 3.5
Classifier: Programming Language :: Python :: 3.6
Classifier: Programming Language :: Python :: 3.7
Classifier: Programming Language :: Python :: 3.8
Classifier: Topic :: Scientific/Engineering :: Physics
Requires-Dist: pandas (>=1.1.2)
Requires-Dist: sqlalchemy
Requires-Dist: pymysql
Requires-Dist: requests
